boruta_shap_min/__init__.py
boruta_shap_min/borutashap.py
boruta_shap_min/shap.py
boruta_shap_min-0.1.4.dist-info/LICENSE
boruta_shap_min-0.1.4.dist-info/METADATA
boruta_shap_min-0.1.4.dist-info/WHEEL
boruta_shap_min-0.1.4.dist-info/RECORD
