Metadata-Version: 2.1
Name: boruta-shap-min
Version: 0.1.4
Summary: Minimal version of BorutaShap
Author: Eoghan Keany
Requires-Python: >=3.11,<4.0
Classifier: Programming Language :: Python :: 3
Classifier: Programming Language :: Python :: 3.11
Requires-Dist: lightgbm (>=4.5.0,<5.0.0)
Requires-Dist: llvmlite (>=0.43.0,<0.44.0)
Requires-Dist: matplotlib (>=3.10.0,<4.0.0)
Requires-Dist: scipy (>=1.14.1,<2.0.0)
Requires-Dist: seaborn (>=0.13.2,<0.14.0)
Requires-Dist: shap (>=0.46.0,<0.47.0)
Requires-Dist: statsmodels (>=0.14.4,<0.15.0)
Requires-Dist: xgboost (>=2.1.3,<3.0.0)
